{"trial_id": "0093", "hyperparameters": {"space": [{"class_name": "Int", "config": {"name": "n_hidden", "default": 2, "conditions": [], "min_value": 0, "max_value": 8, "step": 1, "sampling": "linear"}}, {"class_name": "Int", "config": {"name": "n_neurons", "default": null, "conditions": [], "min_value": 16, "max_value": 256, "step": 16, "sampling": "linear"}}, {"class_name": "Float", "config": {"name": "learning_rate", "default": 1e-06, "conditions": [], "min_value": 1e-06, "max_value": 0.01, "step": null, "sampling": "log"}}, {"class_name": "Choice", "config": {"name": "optimizer", "default": "sgd", "conditions": [], "values": ["sgd", "adam"], "ordered": false}}, {"class_name": "Boolean", "config": {"name": "normalize", "default": false, "conditions": []}}], "values": {"n_hidden": 2, "n_neurons": 224, "learning_rate": 0.009836622769605008, "optimizer": "adam", "normalize": true, "tuner/epochs": 2, "tuner/initial_epoch": 0, "tuner/bracket": 4, "tuner/round": 0}}, "metrics": {"metrics": {"accuracy": {"direction": "max", "observations": [{"value": [0.7977091073989868], "step": 0}]}, "loss": {"direction": "min", "observations": [{"value": [0.5650528073310852], "step": 0}]}, "val_accuracy": {"direction": "max", "observations": [{"value": [0.8263999819755554], "step": 0}]}, "val_loss": {"direction": "min", "observations": [{"value": [0.4516541063785553], "step": 0}]}}}, "score": 0.8263999819755554, "best_step": 0, "status": "COMPLETED", "message": null}